autoloss/__init__.py
autoloss/_autoloss.py
autoloss-1.1.0.dist-info/METADATA
autoloss-1.1.0.dist-info/WHEEL
autoloss-1.1.0.dist-info/RECORD
