Metadata-Version: 2.1
Name: autoloss
Version: 1.1.0
Summary: AutoLoss is a complex optimizer that uses Artifical Intelligence to optimize your neural network
Author: BossBoss2011
Author-email: bogdanelsandu@hotmail.com
Requires-Python: >=3.11,<4.0
Classifier: Programming Language :: Python :: 3
Classifier: Programming Language :: Python :: 3.11
Classifier: Programming Language :: Python :: 3.12
Requires-Dist: numpy (>=2.2.3,<3.0.0)
Requires-Dist: torch (>=2.3.1,<3.0.0)
